approxscimate/__init__.py
approxscimate/cbrt.py
approxscimate/comb.py
approxscimate/perm.py
approxscimate-0.0.4.dist-info/METADATA
approxscimate-0.0.4.dist-info/WHEEL
approxscimate-0.0.4.dist-info/licenses/LICENSE
approxscimate-0.0.4.dist-info/RECORD
